ansys/aedt/toolkits/common/__init__.py
ansys/aedt/toolkits/common/utils.py
ansys/aedt/toolkits/common/backend/__init__.py
ansys/aedt/toolkits/common/backend/api.py
ansys/aedt/toolkits/common/backend/common_properties.toml
ansys/aedt/toolkits/common/backend/constants.py
ansys/aedt/toolkits/common/backend/logger_handler.py
ansys/aedt/toolkits/common/backend/models.py
ansys/aedt/toolkits/common/backend/multithreading_server.py
ansys/aedt/toolkits/common/backend/rest_api.py
ansys/aedt/toolkits/common/backend/thread_manager.py
ansys/aedt/toolkits/common/ui/__init__.py
ansys/aedt/toolkits/common/ui/actions_generic.py
ansys/aedt/toolkits/common/ui/common_properties.toml
ansys/aedt/toolkits/common/ui/logger_handler.py
ansys/aedt/toolkits/common/ui/models.py
ansys/aedt/toolkits/common/ui/common_windows/__init__.py
ansys/aedt/toolkits/common/ui/common_windows/home_menu.py
ansys/aedt/toolkits/common/ui/common_windows/settings_column.py
ansys/aedt/toolkits/common/ui/main_window/__init__.py
ansys/aedt/toolkits/common/ui/main_window/main_window_layout.py
ansys/aedt/toolkits/common/ui/utils/__init__.py
ansys/aedt/toolkits/common/ui/utils/resolution.py
ansys/aedt/toolkits/common/ui/utils/images/__init__.py
ansys/aedt/toolkits/common/ui/utils/images/load_images.py
ansys/aedt/toolkits/common/ui/utils/images/files/ansys-black.svg
ansys/aedt/toolkits/common/ui/utils/images/files/ansys-primary-logo-black.svg
ansys/aedt/toolkits/common/ui/utils/images/files/ansys-primary-logo-white.svg
ansys/aedt/toolkits/common/ui/utils/images/files/ansys-white.svg
ansys/aedt/toolkits/common/ui/utils/images/files/icon.ico
ansys/aedt/toolkits/common/ui/utils/images/files/logo.png
ansys/aedt/toolkits/common/ui/utils/images/files/synopsys-logo.svg
ansys/aedt/toolkits/common/ui/utils/images/files/synopsys_logo.png
ansys/aedt/toolkits/common/ui/utils/images/icons/active_menu.svg
ansys/aedt/toolkits/common/ui/utils/images/icons/additive-print-gold.svg
ansys_aedt_toolkits_common-0.15.0.dist-info/licenses/LICENSE
ansys_aedt_toolkits_common-0.15.0.dist-info/WHEEL
ansys_aedt_toolkits_common-0.15.0.dist-info/METADATA
ansys_aedt_toolkits_common-0.15.0.dist-info/RECORD
