Metadata-Version: 2.4
Name: ansys-aedt-toolkits-common
Version: 0.15.0
Summary: User interface example repository to create your toolkit.
Author-email: "ANSYS, Inc." <pyansys.support@ansys.com>
Maintainer-email: PyAnsys developers <pyansys.maintainers@ansys.com>
Requires-Python: >=3.8
Classifier: Development Status :: 4 - Beta
Classifier: Programming Language :: Python :: 3
Classifier: License :: OSI Approved :: MIT License
Classifier: Operating System :: OS Independent
License-File: LICENSE
Requires-Dist: build==1.3.0
Requires-Dist: twine==6.2.0
Requires-Dist: pyaedt>=0.20.0
Requires-Dist: pydantic>=2.0,<2.13
Requires-Dist: tomli; python_version < '3.12'
Requires-Dist: attrs<25.2.0
Requires-Dist: pyaedt[all]>=0.15.2 ; extra == "all"
Requires-Dist: flask ; extra == "all"
Requires-Dist: pyside6==6.9.2 ; extra == "all"
Requires-Dist: pyqtgraph ; extra == "all"
Requires-Dist: qdarkstyle ; extra == "all"
Requires-Dist: ansys-tools-visualization-interface[pyvistaqt] ; extra == "all"
Requires-Dist: ansys-aedt-toolkits-common[all] ; extra == "doc"
Requires-Dist: recommonmark>=0.7.0,<0.8 ; extra == "doc"
Requires-Dist: pyside6==6.9.2 ; extra == "doc"
Requires-Dist: ansys-sphinx-theme==1.6.0 ; extra == "doc"
Requires-Dist: numpydoc>=1.5.0,<1.10 ; extra == "doc"
Requires-Dist: Sphinx>=7.1.0,<8.3 ; extra == "doc"
Requires-Dist: sphinx-copybutton>=0.5.0,<0.6 ; extra == "doc"
Requires-Dist: sphinx-autobuild==2021.3.14 ; extra == "doc" and ( python_version == '3.8')
Requires-Dist: sphinx-autobuild==2024.10.3 ; extra == "doc" and ( python_version > '3.8')
Requires-Dist: nbsphinx>=0.9.0,<0.10 ; extra == "doc"
Requires-Dist: sphinx_design ; extra == "doc"
Requires-Dist: jupytext ; extra == "doc"
Requires-Dist: ipython>=8.13.0,<9.1 ; extra == "doc"
Requires-Dist: jupyterlab>=4.0.0,<4.5 ; extra == "doc"
Requires-Dist: pypandoc>=1.10.0,<1.16 ; extra == "doc"
Requires-Dist: ipywidgets ; extra == "doc"
Requires-Dist: pyaedt[all]>=0.15.2 ; extra == "tests"
Requires-Dist: flask ; extra == "tests"
Requires-Dist: pyside6==6.9.2 ; extra == "tests"
Requires-Dist: pytest>=7.4.0,<8.5 ; extra == "tests"
Requires-Dist: pytest-cov>=4.0.0,<7.1 ; extra == "tests"
Requires-Dist: pytest-qt>=4.0.0,<4.6 ; extra == "tests"
Requires-Dist: ansys-aedt-toolkits-common[all] ; extra == "tests"
Project-URL: Discussions, https://github.com/ansys/pyaedt-toolkits-common/discussions
Project-URL: Documentation, https://aedt.common.toolkit.docs.pyansys.com
Project-URL: Issues, https://github.com/ansys/pyaedt-toolkits-common/issues
Project-URL: Releases, https://github.com/ansys/pyaedt-toolkits-common/releases
Project-URL: Source, https://github.com/ansys/pyaedt-toolkits-common.git
Provides-Extra: all
Provides-Extra: doc
Provides-Extra: tests
